{
  "isoFields": {
    "0": "ECHO",
    "1": "ECHO",
    "2": "ECHO",
    "3": "ECHO",
    "4": "ECHO",
    "5": "ECHO",
    "6": "ECHO",
    "7": "ECHO",
    "8": "ECHO",
    "9": "ECHO",
    "10": "ECHO",
    "11": "ECHO",
    "12": "ECHO",
    "13": "ECHO",
    "14": "ECHO",
    "15": "ECHO",
    "16": "ECHO",
    "17": "ECHO",
    "18": "ECHO",
    "19": "ECHO",
    "20": "ECHO",
    "21": "ECHO",
    "22": "ECHO",
    "23": "ECHO",
    "24": "ECHO",
    "25": "ECHO",
    "26": "ECHO",
    "27": "ECHO",
    "28": "ECHO",
    "29": "ECHO",
    "30": "ECHO",
    "31": "ECHO",
    "32": "ECHO",
    "33": "ECHO",
    "34": "ECHO",
    "35": "ECHO",
    "36": "ECHO",
    "37": "ECHO",
    "38": "ECHO",
    "39": "00",
    "40": "ECHO",
    "41": "ECHO",
    "42": "ECHO",
    "43": "ECHO",
    "44": "ECHO",
    "45": "ECHO",
    "46": "ECHO",
    "47": "ECHO",
    "48": "ECHO",
    "49": "ECHO",
    "50": "ECHO",
    "51": "ECHO",
    "52": "ECHO",
    "53": "ECHO",
    "54": "ECHO",
    "55": "ECHO",
    "56": "ECHO",
    "57": "ECHO",
    "58": "ECHO",
    "59": "ECHO",
    "60": "ECHO",
    "61": "ECHO",
    "62": "ECHO",
    "63": "ECHO",
    "64": "ECHO",
    "65": "ECHO",
    "66": "ECHO",
    "67": "ECHO",
    "68": "ECHO",
    "69": "ECHO",
    "70": "ECHO",
    "71": "ECHO",
    "72": "ECHO",
    "73": "ECHO",
    "74": "ECHO",
    "75": "ECHO",
    "76": "ECHO",
    "77": "ECHO",
    "78": "ECHO",
    "79": "ECHO",
    "80": "ECHO",
    "81": "ECHO",
    "82": "ECHO",
    "83": "ECHO",
    "84": "ECHO",
    "85": "ECHO",
    "86": "ECHO",
    "87": "ECHO",
    "88": "ECHO",
    "89": "ECHO",
    "90": "ECHO",
    "91": "ECHO",
    "92": "ECHO",
    "93": "ECHO",
    "94": "ECHO",
    "95": "ECHO",
    "96": "ECHO",
    "97": "ECHO",
    "98": "ECHO",
    "99": "ECHO",
    "100": "ECHO",
    "101": "ECHO",
    "102": "ECHO",
    "103": "ECHO",
    "104": "ECHO",
    "105": "ECHO",
    "106": "ECHO",
    "107": "ECHO",
    "108": "ECHO",
    "109": "ECHO",
    "110": "ECHO",
    "111": "ECHO",
    "112": "ECHO",
    "113": "ECHO",
    "114": "ECHO",
    "115": "ECHO",
    "116": "ECHO",
    "117": "ECHO",
    "118": "ECHO",
    "119": "ECHO",
    "120": "ECHO",
    "121": "ECHO",
    "122": "ECHO",
    "123": "ECHO",
    "124": "ECHO",
    "125": "ECHO",
    "126": "ECHO",
    "127": "ECHO",
    "128": "ECHO"
  }
}